mac2win_zip_mcp/__init__.py
mac2win_zip_mcp/server.py
mac2win_zip_mcp-1.0.0.dist-info/METADATA
mac2win_zip_mcp-1.0.0.dist-info/WHEEL
mac2win_zip_mcp-1.0.0.dist-info/entry_points.txt
mac2win_zip_mcp-1.0.0.dist-info/licenses/LICENSE
mac2win_zip_mcp-1.0.0.dist-info/RECORD
