Metadata-Version: 2.4
Name: mac2win-zip-mcp
Version: 1.0.0
Summary: MCP Server for creating Windows-compatible ZIP files from macOS
Project-URL: Homepage, https://github.com/Wordbe/mac2win-zip-mcp
Project-URL: Repository, https://github.com/Wordbe/mac2win-zip-mcp
Project-URL: Issues, https://github.com/Wordbe/mac2win-zip-mcp/issues
Author: mac2win-zip-mcp contributors
License: MIT License
License-File: LICENSE
Keywords: macos,mcp,nfc,nfd,unicode,windows,zip
Classifier: Development Status :: 4 - Beta
Classifier: Intended Audience :: Developers
Classifier: License :: OSI Approved :: MIT License
Classifier: Operating System :: MacOS
Classifier: Programming Language :: Python :: 3
Classifier: Programming Language :: Python :: 3.10
Classifier: Programming Language :: Python :: 3.11
Classifier: Programming Language :: Python :: 3.12
Classifier: Topic :: System :: Archiving :: Compression
Requires-Python: >=3.10
Requires-Dist: mac2win-zip>=1.0.1
Requires-Dist: mcp>=1.9.0
Provides-Extra: dev
Requires-Dist: pytest-cov>=4.0.0; extra == 'dev'
Requires-Dist: pytest>=7.0.0; extra == 'dev'
